army_days/__init__.py
army_days/cli.py
army_days/config.py
army_days/core.py
army_days/date_formatting.py
army_days/models.py
army_days/output.py
army_days/ansi_text/__init__.py
army_days/utils/__init__.py
army_days-0.5.0.dist-info/METADATA
army_days-0.5.0.dist-info/WHEEL
army_days-0.5.0.dist-info/entry_points.txt
army_days-0.5.0.dist-info/licenses/LICENSE
army_days-0.5.0.dist-info/RECORD
