Metadata-Version: 2.4
Name: army-days
Version: 0.5.0
Summary: day countdown program (python edition)
License-File: LICENSE
Requires-Python: >=3.12
Requires-Dist: click>=8.1.7
Requires-Dist: pydantic>=2.9.1
Requires-Dist: python-dateutil>=2.9.0
Requires-Dist: pyyaml>=6.0.2
